ys/__init__.py
ys-0.0.5.dist-info/licenses/LICENSE
ys-0.0.5.dist-info/METADATA
ys-0.0.5.dist-info/WHEEL
ys-0.0.5.dist-info/top_level.txt
ys-0.0.5.dist-info/RECORD
