Metadata-Version: 2.4
Name: ys
Version: 0.0.5
Summary: Special dicts
Home-page: https://github.com/t-c-w/ys
Author: Thor Whalen
License: apache-2.0
Platform: any
License-File: LICENSE
Dynamic: license-file
